Metadata-Version: 1.0
Name: pytdxupdate
Version: 0.4
Summary: update data from pytdx
Home-page: http://www.cnblogs.com/dxf813/
Author: Adam.ding
Author-email: dxf813@126.com
License: UNKNOWN
Platform: UNKNOWN
